olympipe/__init__.py
olympipe/helpers/dag.py
olympipe/helpers/server.py
olympipe/pipes/__init__.py
olympipe/pipes/batch.py
olympipe/pipes/debug.py
olympipe/pipes/explode.py
olympipe/pipes/filter.py
olympipe/pipes/generic.py
olympipe/pipes/instance.py
olympipe/pipes/limit.py
olympipe/pipes/reduce.py
olympipe/pipes/task.py
olympipe/pipes/timebatch.py
olympipe/pipes/timeout.py
olympipe/py.typed
olympipe/shuttable_queue.py
olympipe/types.py
olympipe-1.6.0.dist-info/METADATA
olympipe-1.6.0.dist-info/WHEEL
olympipe-1.6.0.dist-info/licenses/LICENSE
olympipe-1.6.0.dist-info/RECORD
