Metadata-Version: 2.4
Name: olympipe
Version: 1.6.0
Summary: A powerful parallel pipelining tool
License: MIT
License-File: LICENSE
Keywords: pipeline,multiprocessing
Author: Gabriel Kasser
Author-email: gabriel.kasser@gmail.com
Requires-Python: >=3.8,<4.0
Classifier: License :: OSI Approved :: MIT License
Classifier: Programming Language :: Python :: 3
Classifier: Programming Language :: Python :: 3.8
Classifier: Programming Language :: Python :: 3.9
Classifier: Programming Language :: Python :: 3.10
Classifier: Programming Language :: Python :: 3.11
Classifier: Programming Language :: Python :: 3.12
Classifier: Programming Language :: Python :: 3.13
Classifier: Programming Language :: Python :: 3.14
Requires-Dist: dpkt (>=1.9.8,<2.0.0)
Requires-Dist: psutil (>=5.9.5,<6.0.0)
Requires-Dist: setproctitle (>=1.3.3,<2.0.0)
Requires-Dist: tqdm (>=4.66.1,<5.0.0)
Requires-Dist: types-psutil (>=5.9.5.16,<6.0.0.0)
Project-URL: Homepage, https://gitlab.com/gabraken/olympipe
Project-URL: Repository, https://gitlab.com/gabraken/olympipe
